secretsenv/__init__.py
secretsenv/secretsenv.py
secretsenv/classes/__init__.py
secretsenv/classes/config.py
secretsenv/classes/conftemplates.py
secretsenv/classes/dump.py
secretsenv/classes/exceptions.py
secretsenv/classes/loadinifiles.py
secretsenv/classes/run.py
secretsenv/classes/tools.py
secretsenv/classes/vaults.py
secretsenv/modules/__init__.py
secretsenv/modules/keepass.py
secretsintheenv-1.0.4.dist-info/LICENSE
secretsintheenv-1.0.4.dist-info/METADATA
secretsintheenv-1.0.4.dist-info/WHEEL
secretsintheenv-1.0.4.dist-info/entry_points.txt
secretsintheenv-1.0.4.dist-info/top_level.txt
secretsintheenv-1.0.4.dist-info/RECORD
