Metadata-Version: 2.1
Name: secretsintheenv
Version: 1.0.4
Summary: Tool for raising a configured shell with all required secrets, retrieved from compatible vaults, for your project onto memory in user space
Author-email: Yohnah <yohnah@gmail.com>
Project-URL: Homepage, https://github.com/Yohnah/secretsenv
Project-URL: Bug Tracker, https://github.com/Yohnah/secretsenv/issues
Classifier: Programming Language :: Python :: 3
Classifier: License :: OSI Approved :: GNU General Public License v3 (GPLv3)
Classifier: Operating System :: MacOS
Classifier: Operating System :: Microsoft
Classifier: Operating System :: Microsoft :: Windows
Classifier: Operating System :: POSIX :: Linux
Classifier: Environment :: Console
Classifier: Intended Audience :: Developers
Classifier: Intended Audience :: System Administrators
Classifier: Topic :: Security
Classifier: Topic :: System :: Shells
Classifier: Topic :: Utilities
Requires-Python: >=3.7
License-File: LICENSE
Requires-Dist: pykeepass (==4.0.3)
